<?xml version="1.0" encoding="UTF-8"?>
<person xmlns="http://www.tei-c.org/ns/1.0" xml:id="pers_DE-588-117589144" role="main">
    <idno type="gnd">(DE-588)117589144</idno>
    <persName type="reg"><surname>Bernoulli</surname><forename>Nicolaus II</forename><genName/><roleName/></persName>
    <birth when="1695">1695</birth>
    <death when="1726">1726</death>
    <note>Nicolaus II Bernoulli ist der Sohn von Johann I B. und Bruder von Daniel I B. und Johann II B. Er wurde von seinem Vater mathematisch geschult. Er erlangte 1711 den Magister der Philosophie und wurde 1715 Dr. iur. 1716-17 hielt er sich in Venedig auf und wurde ab 1723 Professor der Jurisprudenz an der Berner Oberen Schule. Ab 1725 Professor der Mathematik an der neu gegründeten Akademie der Wissenschaften in St. Petersburg, wo er nach nur neun Monaten verstirbt. Seine mathematischen Leistungen betreffen v.a. die Orthogonaltrajektorien und die Analyse der Riccati'schen Differentialgleichung. Im Streit mit den Newtonianern steht er seinem Vater zur Seite.</note>
    <figure>
    	<graphic url="https://upload.wikimedia.org/wikipedia/commons/7/74/Bernoulli_Nicolaus%28II%29.jpeg"/>
        <figDesc><ref target="https://commons.wikimedia.org/wiki/File:Bernoulli_Nicolaus(II).jpeg">Ölgemälde von Johann Rudolf Huber</ref>. Bildquelle: Wikimedia Commons.</figDesc>
    </figure>
    <bibl/>
</person>
