<?xml version='1.0' encoding='utf-8'?>
<biblStruct xmlns="http://www.tei-c.org/ns/1.0" type="book" corresp="http://zotero.org/groups/4835449/items/JJAW3IPT" xml:id="biblio_JJAW3IPT"><monogr><title level="m">Fasciculus Dissertationem Medicarum Selectiorum, Quibus Curiosa non minus quàm Utilia cientiæ Apollineæ Themata Diligenter pertractata, etc; adcuratè exposita sistuntur</title><author><forename>Theodor</forename><surname>Zwinger</surname></author><imprint><pubPlace>Basel</pubPlace><publisher>Ludwig Koenig</publisher><date>1710</date></imprint></monogr><note>Typis Joh. Conradi à Mechel


</note><note type="tags"><note type="tag">Entwurf</note></note></biblStruct>