<?xml version="1.0" encoding="UTF-8"?>
<biblStruct xmlns="http://www.tei-c.org/ns/1.0" type="journalArticle" corresp="http://zotero.org/groups/4835449/items/94ATHNKN" xml:id="biblio_94ATHNKN">
  <analytic>
    <title level="a">Examen Principiorum Mechanicae, et Demonstrationes Geometricae de Compositione et Resolutione Virium</title>
    <title type="short">Examen principiorum mechanicae</title>
    <author>
      <forename>Daniel I</forename>
      <surname>Bernoulli</surname>
    </author>
  </analytic>
  <monogr>
    <title level="j">Commentarii Academiae Scientiarum Imperialis Petropolitanae</title>
    <imprint>
      <pubPlace>Petropoli</pubPlace>
      <biblScope unit="volume">I</biblScope>
      <biblScope unit="issue">1726</biblScope>
      <biblScope unit="page">126-142</biblScope>
      <publisher>Typis Academiae</publisher>
      <date>1728</date>
      <note type="url">https://www.biodiversitylibrary.org/item/113649#page/159/mode/1up</note>
    </imprint>
  </monogr>
  <note>DanIB WV: St.9. | Quelle: Word-Referenz DanB-Werke_St-Mm1996.docx | Rohangabe: Examen Principiorum Mechanicae, et Demonstrationes Geometricae de Compositione et Resolutione Virium: CP I, 1726 (1728), pp.126-142 - Werke 3, pp.119-135 - [französische Übersetzung von J.Dhombres:] Examen des Principes de la Mécanique et démonstrations géométriques de la composition et de la résolution des forces: Sciences et techniques en perspective, vol.11 (1986/7), Nantes 1987, pp.39-58.


</note>
</biblStruct>
