<?xml version='1.0' encoding='utf-8'?>
<biblStruct xmlns="http://www.tei-c.org/ns/1.0" type="book" corresp="http://zotero.org/groups/4835449/items/G34ECXQ3" xml:id="biblio_G34ECXQ3"><monogr><title level="m">Pantagruel, roy des Dipsodes, restitué à son naturel: avec ses faictz et prouesses espouventables, composés par feu M. Alcofribas, abstracteur de quinte essence</title><author><forename>François</forename><surname>Rabelais</surname></author><imprint><pubPlace>Lyon</pubPlace><publisher>E. Dolet</publisher><date>1542</date><note type="url">http://services.bibliothek.kit.edu/kvk/view-title/index.php?katalog=EROMM_WEBSEARCH&amp;url=http%3A%2F%2Fwww.eromm.org%2Fopensearch%2Fresolver.php%3Furl%3Dhttp%253A%252F%252Fgallica.bnf.fr%252Fark%253A%252F12148%252Fbpt6k792829%26s%3Do%26i%3D2&amp;showCoverImg=1</note></imprint></monogr></biblStruct>