<?xml version='1.0' encoding='utf-8'?>
<biblStruct xmlns="http://www.tei-c.org/ns/1.0" type="journalArticle" corresp="http://zotero.org/groups/4835449/items/NAM5ZEAD" xml:id="biblio_NAM5ZEAD"><analytic><title level="a">Lettre... sur la jonction de l’Amérique à l’Asie</title><author><forename>Louis</forename><surname>Bourguet</surname></author></analytic><monogr><title level="j">Mercure Suisse, ou Recueil de Nouvelles Historiques, Politiques, Litteraires &amp; Curieuses.</title><imprint><biblScope unit="volume">1735</biblScope><biblScope unit="issue">Juillet</biblScope><biblScope unit="page">67-97</biblScope><date>1735</date></imprint></monogr><note type="tags"><note type="tag">kein Digitalisat</note><note type="tag">Abgetippt</note></note></biblStruct>