<?xml version="1.0" encoding="UTF-8"?>
<biblStruct xmlns="http://www.tei-c.org/ns/1.0" type="book" corresp="http://zotero.org/groups/4835449/items/5H9TXG5Q" xml:id="biblio_5H9TXG5Q">
  <monogr>
    <author>
      <forename>Joh. Leonhard</forename>
      <surname>Walz</surname>
    </author>
    <respStmt>
      <resp>contributor</resp>
      <persName>
        <forename>Johann II</forename>
        <surname>Bernoulli</surname>
      </persName>
    </respStmt>
    <title level="m">Theses miscellaneae ex Jure Naturae desumtae, quas [...] pro vacante Juris Naturae et Philosophiae Moralis Cathedra publice defendet Johannes Bernoulli, Joh. Fil. J.U.D. Respondente juvene florentissimo Joh. Leonhardo Walz, Durlaco - Roetelano. Die 16. Februarii 1734. H.L.Q.S.</title>
    <idno type="callNumber">UB Basel, UBH VB M 133:11</idno>
    <imprint>
      <pubPlace>Basileae</pubPlace>
      <publisher>Joh. H. Decker</publisher>
      <date>1734</date>
      <note type="url">https://doi.org/10.3931/e-rara-134662</note>
    </imprint>
  </monogr>
</biblStruct>
