<?xml version='1.0' encoding='utf-8'?>
<biblStruct xmlns="http://www.tei-c.org/ns/1.0" type="journalArticle" corresp="http://zotero.org/groups/4835449/items/9DRJZCT2" xml:id="biblio_9DRJZCT2"><analytic><title level="a">Dissertatio de igne, in qua ejus natura et proprietates explicantur: Occasione Quaestionis, cum praemio annexo, ab Illustrissimâ Academia Scientiarum Regia Parisina pro anno 1738 propositae, ejusdem Academiae judicio aequo submissa: Cui Praemium, in tres partes divisum, pro unâ ex illis addictum fuit.</title><idno type="DOI">https://doi.org/10.3931/e-rara-12824</idno><author><forename>Leonhard</forename><surname>Euler</surname></author></analytic><monogr><title level="j">Recueil des Pieces qui ont remporté le Prix de l'Academie royale des sciences depuis leur fondation jusqu'à present. Avec quelques Pieces qui ont été composées à l'occasion de ces Prix.</title><imprint><biblScope unit="volume">IV, 1738-1740</biblScope><biblScope unit="issue">Nr. I</biblScope><date>1752</date></imprint></monogr><note>Link auf Startseite: https://www.e-rara.ch/zut/content/zoom/3936371


</note><note type="tags"><note type="tag">Entwurf</note></note></biblStruct>