<?xml version='1.0' encoding='utf-8'?>
<biblStruct xmlns="http://www.tei-c.org/ns/1.0" type="journalArticle" corresp="http://zotero.org/groups/4835449/items/ZV9GWR7V" xml:id="biblio_ZV9GWR7V"><analytic><title level="a">Reflexions sur les regles de la condensation de l’air</title><author><forename>Jacques</forename><surname>Cassini</surname></author></analytic><monogr><title level="j">Mémoires de l'Académie Royale des Sciences</title><imprint><biblScope unit="issue">1705</biblScope><biblScope unit="page">72-74</biblScope><date>1706</date></imprint></monogr></biblStruct>