<?xml version='1.0' encoding='utf-8'?>
<biblStruct xmlns="http://www.tei-c.org/ns/1.0" type="book" corresp="http://zotero.org/groups/4835449/items/HACPXJEK" xml:id="biblio_HACPXJEK"><monogr><title level="m">Enchiridion mathematicum ...</title><author><forename>Johann Jakob</forename><surname>Scheuchzer</surname></author><imprint><pubPlace>Tiguri</pubPlace><publisher>H. Bodmer</publisher><date>1714</date><note type="url">https://doi.org/10.3931/e-rara-89392</note></imprint></monogr><note type="tags"><note type="tag">Legacy</note></note></biblStruct>