<?xml version='1.0' encoding='utf-8'?>
<biblStruct xmlns="http://www.tei-c.org/ns/1.0" type="book" corresp="http://zotero.org/groups/4835449/items/Z98M7XJH" xml:id="biblio_Z98M7XJH">
     <monogr>
      <title level="m">Oeconomiae divinae libri sex, in quibus dei erga homines proposita, agendi rationes, atque opera demonstrantur.</title>
      <author><forename>Pierre</forename><surname>Poiret</surname></author>
      <imprint>
       <pubPlace>Francofurti</pubPlace>
       <publisher>T. Fritsch</publisher>
       <date>1705</date>
       <note type="url">http://resolver.staatsbibliothek-berlin.de/SBB0002A2CE00010000</note>
      </imprint>
     </monogr>
     <note>Digitalisat: Volumen Secundum http://resolver.staatsbibliothek-berlin.de/SBB0002A2CE00020000


</note>
     <note type="tags"><note type="tag">Abgetippt</note></note>
    </biblStruct>
    