<?xml version='1.0' encoding='utf-8'?>
<biblStruct xmlns="http://www.tei-c.org/ns/1.0" type="book" corresp="http://zotero.org/groups/4835449/items/USXHT5CW" xml:id="biblio_USXHT5CW"><monogr><title level="m">De causa gravitatis physica generali disquisitio experimentalis. Quae praemium... retulit: anno 1728</title><author><forename>Georg Bernhard</forename><surname>Bilfinger</surname></author><imprint><pubPlace>Paris</pubPlace><publisher>C. Jombert</publisher><date>1728</date></imprint></monogr></biblStruct>