<?xml version='1.0' encoding='utf-8'?>
<biblStruct xmlns="http://www.tei-c.org/ns/1.0" type="book" corresp="http://zotero.org/groups/4835449/items/IHM5K8GW" xml:id="biblio_IHM5K8GW"><monogr><title level="m">Christiani Wolfii Consideratio Physico - Mathematica Hiemis proxime praeterlapsae, hoc est, An. MDCCIX. Quam sub Ipsius Praesidio in Academia Halensi ad diem XIII. Iunii ejusdem Anni horis antemeriedianis in Auditorio Majori defendit Georgius Remus, Gedanensi</title><author><forename>Christian</forename><surname>Wolff</surname></author><imprint><pubPlace>Halle</pubPlace><publisher>Chr A. Zeitler</publisher><date>1709</date><note type="url">http://digitale.bibliothek.uni-halle.de/vd18/content/pageview/4047435</note></imprint></monogr></biblStruct>