<?xml version="1.0" encoding="UTF-8"?>
<biblStruct xmlns="http://www.tei-c.org/ns/1.0" type="journalArticle" corresp="http://zotero.org/groups/4835449/items/GNDPPM9J" xml:id="biblio_GNDPPM9J">
  <analytic>
    <title level="a">Continuatio argumenti De Mensura Sortis ad fortuitam Successionem rerum naturaliter contingentium applicata</title>
    <title type="short">Continuatio argumenti De Mensura Sortis ad fortuitam Successionem</title>
    <author>
      <forename>Daniel I</forename>
      <surname>Bernoulli</surname>
    </author>
  </analytic>
  <monogr>
    <title level="j">Novi Commentarii Academiae Scientiarum Imperialis Petropolitanae</title>
    <imprint>
      <pubPlace>Petropoli</pubPlace>
      <biblScope unit="volume">XV</biblScope>
      <biblScope unit="issue">1770</biblScope>
      <biblScope unit="page">3-28</biblScope>
      <date>1771</date>
    </imprint>
  </monogr>
  <note>DanIB WV: St.59b. | Quelle: Word-Referenz DanB-Werke_St-Mm1996.docx | Rohangabe: Continuatio argumenti De Mensura Sortis ad fortuitam Successionem rerum naturaliter contingentium applicata: NCP XV, 1770 (1771), pp.3-28 - Werke 2, pp.341-360.


</note>
  <note>DanIB-ID: St.59b

</note>
  <note type="tags">
    <note type="tag">BEBB import candidate</note>
    <note type="tag">DanIB Werkverzeichnis</note>
  </note>
</biblStruct>
