<?xml version="1.0" encoding="UTF-8"?>
<biblStruct xmlns="http://www.tei-c.org/ns/1.0" type="journalArticle" corresp="http://zotero.org/groups/4835449/items/WDDTD98D" xml:id="biblio_WDDTD98D">
  <analytic>
    <title level="a">De Variatione motuum a Percussione excentrica</title>
    <author>
      <forename>Daniel I</forename>
      <surname>Bernoulli</surname>
    </author>
  </analytic>
  <monogr>
    <title level="j">Commentarii Academiae Scientiarum Imperialis Petropolitanae</title>
    <imprint>
      <pubPlace>Petropoli</pubPlace>
      <biblScope unit="volume">IX</biblScope>
      <biblScope unit="issue">1737</biblScope>
      <biblScope unit="page">189-206</biblScope>
      <publisher>Typis Academiae</publisher>
      <date>1744</date>
    </imprint>
  </monogr>
  <note>DanIB WV: St.27. | Quelle: Word-Referenz DanB-Werke_St-Mm1996.docx | Rohangabe: De Variatione motuum a Percussione excentrica: CP IX, 1737 (1744), pp.189-206 - Werke 3, pp.145-159.

</note>
  <note>DanIB-ID: St.27

</note>
  <note type="tags">
    <note type="tag">BEBB import candidate</note>
    <note type="tag">DanIB Werkverzeichnis</note>
  </note>
</biblStruct>
