<?xml version='1.0' encoding='utf-8'?>
<biblStruct xmlns="http://www.tei-c.org/ns/1.0" type="book" corresp="http://zotero.org/groups/4835449/items/NZ9LGA6Q" xml:id="biblio_NZ9LGA6Q"><monogr><title level="m">Traité du nivellement, avec une relation de quelques Nivellemens faits par ordre du Roy. Et un Abbregé de a Mesure de la Terre</title><author><forename>Jean</forename><surname>Picard</surname></author><imprint><pubPlace>Paris</pubPlace><publisher>F. Montalant</publisher><date>1728</date><note type="url">https://books.google.de/books?id=r6sWAAAAQAAJ&amp;hl=de&amp;pg=PP5#v=onepage&amp;q&amp;f=false</note></imprint></monogr><note type="tags"><note type="tag">Link nicht permanent</note><note type="tag">Abgetippt</note></note></biblStruct>