<?xml version='1.0' encoding='utf-8'?>
<biblStruct xmlns="http://www.tei-c.org/ns/1.0" type="journalArticle" corresp="http://zotero.org/groups/4835449/items/HQEGPSVS" xml:id="biblio_HQEGPSVS"><analytic><title level="a">Letter to Dr. Mead, Coll. Med. Lond. et Soc. Reg. S. concerning an Experiment, whereby it has been attempted to shew the falsity of the common Opinion, in relation to the force of Bodies in Motion</title><author><forename>Henry</forename><surname>Pemberton</surname></author></analytic><monogr><title level="j">Philosophical Transacations</title><imprint><biblScope unit="volume">Nr. 371</biblScope><biblScope unit="issue">April and May 1722</biblScope><biblScope unit="page">57-68</biblScope><date>1722</date></imprint></monogr><note type="tags"><note type="tag">Abgetippt</note><note type="tag">Digitalisat nicht gesucht</note></note></biblStruct>