<?xml version="1.0" encoding="UTF-8"?>
<biblStruct xmlns="http://www.tei-c.org/ns/1.0" type="journalArticle" corresp="http://zotero.org/groups/4835449/items/X53GAVLH" xml:id="biblio_X53GAVLH">
  <analytic>
    <title level="a">Sur les nouvelles Aiguilles d'inclinaison, faites à Basle par M. Dietric</title>
    <author>
      <forename>Daniel I</forename>
      <surname>Bernoulli</surname>
    </author>
  </analytic>
  <monogr>
    <title level="j">Le Journal des Sçavans</title>
    <imprint>
      <pubPlace>Paris</pubPlace>
      <biblScope unit="issue">Janvier</biblScope>
      <biblScope unit="page">14-24</biblScope>
      <date>1757</date>
    </imprint>
  </monogr>
  <note>DanIB WV: St.49. | Quelle: Word-Referenz DanB-Werke_St-Mm1996.docx | Rohangabe: Sur les nouvelles Aiguilles d'inclinaison, faites à Basle par M. Dietric: JS 1757 (Janvier), pp.14-24 = JSA t.XXV (Janvier 1757), pp.27-50 [teilweise, unter dem Titel: Memoire adressé à Messieurs les Auteurs du Journal des Sçavans] -Acta Helvetica, vol.III (1758), pp.233-249 - Werke 7, pp.140-151.

</note>
  <note>DanIB-ID: St.49

</note>
  <note type="tags">
    <note type="tag">BEBB import candidate</note>
    <note type="tag">DanIB Werkverzeichnis</note>
  </note>
</biblStruct>
