<?xml version="1.0" encoding="UTF-8"?>
<org xmlns="http://www.tei-c.org/ns/1.0" xml:id="org_DE-588-10092421-9">
    <idno type="gnd">(DE-588)10092421-9</idno>
    <orgName type="reg" from="1229" to="1797">Senat der Republik Venedig</orgName>
    <orgName type="alt">Consiglio dei Pregadi</orgName>
    <location>
        <placeName>Venedig</placeName>
        <country>Italien</country>
    </location>
    <ptr type="wikipedia" target="https://it.wikipedia.org/wiki/Consiglio_dei_Pregadi"/>
    <note type="description">
                    <bibl/>
                </note>
    <note type="internal"></note>
</org>

