<?xml version="1.0" encoding="UTF-8"?>
<person xmlns="http://www.tei-c.org/ns/1.0" xml:id="pers_DE-588-123521041">
    <idno type="gnd">(DE-588)123521041</idno>
    <persName type="reg">
        <surname>Ghetaldi</surname>
        <forename>Marino</forename>
        <genName/>
        <roleName/>
    </persName>
    <gender value="M">male</gender>
    <birth><date when="1568"/><placeName/></birth>
    <death><date when="1626"/><placeName/></death>
    <note type="bio"/>
    <note type="internal">https://mathshistory.st-andrews.ac.uk/Biographies/Ghetaldi/</note>
    <bibl/>
</person>