<?xml version="1.0" encoding="UTF-8"?>
<person xmlns="http://www.tei-c.org/ns/1.0" xml:id="pers_DE-588-138244740X">
    <idno type="gnd">(DE-588)138244740X</idno>
    <persName type="reg">
        <surname>Frey</surname>
        <forename>Johann Jakob</forename>
        <genName/>
        <roleName/>
    </persName>
    <gender value="M">male</gender>
    <birth><date when="1656"/><placeName/></birth>
    <death><date when="1722"/><placeName/></death>
    <note type="bio"/>
    <note type="internal"><!-- https://www.hfls.ch/humo-gen/family/1/F73286?main_person=I220150 https://www.stroux.org/patriz_f/stQV_f/FyJ_f.pdf --></note>
    <bibl/>
</person>