<?xml version="1.0" encoding="UTF-8"?><?xml-stylesheet type="text/css" href="Einzeldaten_test.css"?><place xml:id="place_WEI-marmou" xmlns="http://www.tei-c.org/ns/1.0"><placeName xml:lang="de" type="Weiteres">Kloster Marmoutier (Tours)</placeName><location><country>FR</country><geo decls="lon_wgs84_dd">0.716879</geo><geo decls="lat_wgs84_dd">47.402923</geo></location><placeName xml:lang="en">Marmoutier Abbey (Tours)</placeName><placeName xml:lang="fr">Abbaye de Marmoutier (Tours)</placeName><placeName xml:lang="la"></placeName><ptr target="https://de.wikipedia.org/wiki/Kloster_Marmoutier_(Tours)" type="wikipedia"/><ptr target="http://fakeURL.com" type="geonames"/><note hand="intern"></note></place>