<?xml version="1.0" encoding="UTF-8"?><?xml-stylesheet type="text/css" href="Einzeldaten_test.css"?><place xml:id="place_GEO-3178229" xmlns="http://www.tei-c.org/ns/1.0"><placeName xml:lang="de" type="Gemeinde">Como</placeName><location><country>IT</country><geo decls="lon_wgs84_dd">9.0832</geo><geo decls="lat_wgs84_dd">45.80819</geo></location><placeName xml:lang="en">Como</placeName><placeName xml:lang="fr">Côme</placeName><placeName xml:lang="la">Novum Comum</placeName><ptr target="https://en.wikipedia.org/wiki/Como" type="wikipedia"/><ptr target="https://www.geonames.org/3178229" type="geonames"/><note hand="intern"></note></place>
