<?xml version="1.0" encoding="UTF-8"?><?xml-stylesheet type="text/css" href="Einzeldaten_test.css"?><place xml:id="place_GEO-2905290" xmlns="http://www.tei-c.org/ns/1.0"><placeName xml:lang="de" type="Gemeinde">Hessisch Oldendorf</placeName><location><country>DE</country><geo decls="lon_wgs84_dd">9.24913</geo><geo decls="lat_wgs84_dd">52.17269</geo></location><placeName xml:lang="en"></placeName><placeName xml:lang="fr"></placeName><placeName xml:lang="la">Vicus Vetus Hassicus</placeName><ptr target="http://fakeURL.com" type="wikipedia"/><ptr target="https://www.geonames.org/2905290" type="geonames"/><note hand="intern"></note></place>